src/contextual/__init__.py
src/contextual/contextual.py
cclient-0.0.1.dist-info/METADATA
cclient-0.0.1.dist-info/WHEEL
cclient-0.0.1.dist-info/licenses/LICENSE.md
cclient-0.0.1.dist-info/RECORD
